LICENSE
MANIFEST.in
README.md
requirements.txt
setup.py
test-requirements.txt
src/__init__.py
src/__init__.pyc
src/action_regex.py
src/action_regex.pyc
src/autopylint.py
src/autopylint.pyc
src/repair_regex.py
src/repair_regex.pyc
src/table_regex.py
src/table_regex.pyc