Metadata-Version: 1.0
Name: autopylint
Version: 0.0.4
Summary: Tool for automatically applying fixes to errors/warnings identified by pylint
Home-page: UNKNOWN
Author: Hugh Brown
Author-email: hughdbrown@yahoo.com
License: UNKNOWN
Platform: UNKNOWN
